{"v":5,"entries":{"animations-error--default":{"type":"story","id":"animations-error--default","name":"Default","title":"Animations/Error","importPath":"./src/animations/error/Error.stories.tsx","componentPath":"./src/animations/error/Error.tsx","tags":["dev","test"]},"animations-info--default":{"type":"story","id":"animations-info--default","name":"Default","title":"Animations/Info","importPath":"./src/animations/info/Info.stories.tsx","componentPath":"./src/animations/info/Info.tsx","tags":["dev","test"]},"animations-loading--default":{"type":"story","id":"animations-loading--default","name":"Default","title":"Animations/Loading","importPath":"./src/animations/loading/Loading.stories.tsx","componentPath":"./src/animations/loading/default/Loading.tsx","tags":["dev","test"]},"animations-loading--ai-loading":{"type":"story","id":"animations-loading--ai-loading","name":"AI Loading","title":"Animations/Loading","importPath":"./src/animations/loading/Loading.stories.tsx","componentPath":"./src/animations/loading/default/Loading.tsx","tags":["dev","test"]},"animations-success--default":{"type":"story","id":"animations-success--default","name":"Default","title":"Animations/Success","importPath":"./src/animations/success/Success.stories.tsx","componentPath":"./src/animations/success/Success.tsx","tags":["dev","test"]},"animations-warning--default":{"type":"story","id":"animations-warning--default","name":"Default","title":"Animations/Warning","importPath":"./src/animations/warning/Warning.stories.tsx","componentPath":"./src/animations/warning/Warning.tsx","tags":["dev","test"]},"feedback-alertbox--info":{"type":"story","id":"feedback-alertbox--info","name":"Info","title":"Feedback/AlertBox","importPath":"./src/components/alertBox/AlertBox.stories.tsx","tags":["dev","test"]},"feedback-alertbox--success":{"type":"story","id":"feedback-alertbox--success","name":"Success","title":"Feedback/AlertBox","importPath":"./src/components/alertBox/AlertBox.stories.tsx","tags":["dev","test"]},"feedback-alertbox--error":{"type":"story","id":"feedback-alertbox--error","name":"Error","title":"Feedback/AlertBox","importPath":"./src/components/alertBox/AlertBox.stories.tsx","tags":["dev","test"]},"feedback-alertbox--warning":{"type":"story","id":"feedback-alertbox--warning","name":"Warning","title":"Feedback/AlertBox","importPath":"./src/components/alertBox/AlertBox.stories.tsx","tags":["dev","test"]},"components-button--primary":{"type":"story","id":"components-button--primary","name":"Primary","title":"Components/Button","importPath":"./src/components/button/Button.stories.tsx","tags":["dev","test"]},"components-button--secondary":{"type":"story","id":"components-button--secondary","name":"Secondary","title":"Components/Button","importPath":"./src/components/button/Button.stories.tsx","tags":["dev","test"]},"components-button--contained":{"type":"story","id":"components-button--contained","name":"Contained","title":"Components/Button","importPath":"./src/components/button/Button.stories.tsx","tags":["dev","test"]},"components-button--danger":{"type":"story","id":"components-button--danger","name":"Danger","title":"Components/Button","importPath":"./src/components/button/Button.stories.tsx","tags":["dev","test"]},"components-codesnippet--default":{"type":"story","id":"components-codesnippet--default","name":"Default","title":"Components/CodeSnippet","importPath":"./src/components/codeSnippet/CodeSnippet.stories.tsx","componentPath":"./src/components/codeSnippet/CodeSnippet.tsx","tags":["dev","test"]},"feedback-emptystate--default":{"type":"story","id":"feedback-emptystate--default","name":"Default","title":"Feedback/EmptyState","importPath":"./src/components/emptyStateComponent/EmptyStateComponent.stories.tsx","tags":["dev","test"]},"feedback-feedback--success":{"type":"story","id":"feedback-feedback--success","name":"Success","title":"Feedback/Feedback","importPath":"./src/components/feedback/Feedback.stories.tsx","tags":["dev","test"]},"feedback-feedback--error":{"type":"story","id":"feedback-feedback--error","name":"Error","title":"Feedback/Feedback","importPath":"./src/components/feedback/Feedback.stories.tsx","tags":["dev","test"]},"feedback-feedback--loading":{"type":"story","id":"feedback-feedback--loading","name":"Loading","title":"Feedback/Feedback","importPath":"./src/components/feedback/Feedback.stories.tsx","tags":["dev","test"]},"feedback-feedback--ai-loading":{"type":"story","id":"feedback-feedback--ai-loading","name":"AI Loading","title":"Feedback/Feedback","importPath":"./src/components/feedback/Feedback.stories.tsx","tags":["dev","test"]},"feedback-infobox--default":{"type":"story","id":"feedback-infobox--default","name":"Default","title":"Feedback/InfoBox","importPath":"./src/components/infoBox/InfoBox.stories.tsx","tags":["dev","test"]},"components-optioncard--default":{"type":"story","id":"components-optioncard--default","name":"Default","title":"Components/OptionCard","importPath":"./src/components/optionCard/OptionCard.stories.tsx","tags":["dev","test"]},"feedback-pluginnotconfigured--default":{"type":"story","id":"feedback-pluginnotconfigured--default","name":"Default","title":"Feedback/PluginNotConfigured","importPath":"./src/components/pluginNotConfigured/PluginNotConfigured.stories.tsx","componentPath":"./src/components/pluginNotConfigured/PluginNotConfigured.tsx","tags":["dev","test"]},"components-tablecomponent--default":{"type":"story","id":"components-tablecomponent--default","name":"Default","title":"Components/TableComponent","importPath":"./src/components/tableComponent/TableComponent.stories.tsx","componentPath":"./src/components/tableComponent/TableComponent.tsx","tags":["dev","test"]},"icons-veelogo--default":{"type":"story","id":"icons-veelogo--default","name":"Default","title":"Icons/VeeLogo","importPath":"./src/icons/VeeLogo.stories.tsx","componentPath":"./src/icons/VeeLogo.tsx","tags":["dev","test"]},"icons-assistantaimenuicon--default":{"type":"story","id":"icons-assistantaimenuicon--default","name":"Default","title":"Icons/AssistantAIMenuIcon","importPath":"./src/icons/assistant-ai-menu-icon.stories.tsx","componentPath":"./src/icons/assistant-ai-menu-icon.tsx","tags":["dev","test"]},"icons-emptystateicon--default":{"type":"story","id":"icons-emptystateicon--default","name":"Default","title":"Icons/EmptyStateIcon","importPath":"./src/icons/emoty-state-icon.stories.tsx","componentPath":"./src/icons/empty-state-icon.tsx","tags":["dev","test"]},"icons-fixedoptionsicon--default":{"type":"story","id":"icons-fixedoptionsicon--default","name":"Default","title":"Icons/FixedOptionsIcon","importPath":"./src/icons/fixed-options-icon.stories.tsx","componentPath":"./src/icons/fixed-options-icon.tsx","tags":["dev","test"]},"icons-pluginicon--default":{"type":"story","id":"icons-pluginicon--default","name":"Default","title":"Icons/PluginIcon","importPath":"./src/icons/plugin-icon.stories.tsx","componentPath":"./src/icons/plugin-icon.tsx","tags":["dev","test"]},"icons-pluginnotconfiguredicon--default":{"type":"story","id":"icons-pluginnotconfiguredicon--default","name":"Default","title":"Icons/PluginNotConfiguredIcon","importPath":"./src/icons/plugin-not-configured-icon.stories.tsx","componentPath":"./src/icons/plugin-not-configured-icon.tsx","tags":["dev","test"]},"icons-scaffolderaiicon--default":{"type":"story","id":"icons-scaffolderaiicon--default","name":"Default","title":"Icons/ScaffolderAIIcon","importPath":"./src/icons/scaffolder-ai-icon.stories.tsx","componentPath":"./src/icons/scaffolder-ai-icon.tsx","tags":["dev","test"]},"icons-stackicon--default":{"type":"story","id":"icons-stackicon--default","name":"Default","title":"Icons/StackIcon","importPath":"./src/icons/stack-icon.stories.tsx","componentPath":"./src/icons/stack-icon.tsx","tags":["dev","test"]},"icons-veesettingsicon--default":{"type":"story","id":"icons-veesettingsicon--default","name":"Default","title":"Icons/VeeSettingsIcon","importPath":"./src/icons/vee-settings-icon.stories.tsx","componentPath":"./src/icons/vee-settings-icon.tsx","tags":["dev","test"]},"examples-layout-contentlayout--default":{"type":"story","id":"examples-layout-contentlayout--default","name":"Default","title":"Examples/Layout/ContentLayout","importPath":"./src/layout/contentLayout/ContentLayout.stories.tsx","tags":["dev","test"]}}}